{
  "id": "cannon",
  "sprite": {
    "texture": "cannon",
    "offset": {
      "x": 0,
      "y": -22
    }
  },
  "type": "weapon",
  "cooldown": 0.5,
  "recoil": 400.0,
  "uses": 3,
  "mount_offset": {
    "x": -16,
    "y": -22
  },
  "effect_offset": {
    "x": 36,
    "y": 0
  },
  "sound_effect": "shoot",
  "effect": {
    "type": "triggered_effect",
    "trigger": "both",
    "velocity": {
      "x": 1000.0,
      "y": -100.0
    },
    "size": {
      "x": 17,
      "y": 17
    },
    "timed_trigger": 1.5,
    "triggered_effect": {
      "type": "circle_collider",
      "radius": 64,
      "is_friendly_fire": true,
      "particle_effect": "hit",
      "sound_effect": "explode"
    },
    "animation": {
      "texture": "cannon_ball",
      "animations": [
        {
          "id": "armed",
          "row": 0,
          "frames": 1,
          "fps": 1
        }
      ],
      "should_autoplay": true
    }
  },
  "collider_size": {
    "x": 64,
    "y": 24
  },
  "animation": {
    "texture": "cannon",
    "animations": [
      {
        "id": "idle",
        "row": 0,
        "frames": 1,
        "fps": 1
      },
      {
        "id": "attack",
        "row": 1,
        "frames": 4,
        "fps": 8
      }
    ]
  }
}